lxd_client/__init__.py
lxd_client/api/__init__.py
lxd_client/api/certificates/__init__.py
lxd_client/api/certificates/delete_fingerprint.py
lxd_client/api/certificates/get_certificates.py
lxd_client/api/certificates/get_certificates_by_finger_print.py
lxd_client/api/certificates/patch_fingerprint.py
lxd_client/api/certificates/post_certificates.py
lxd_client/api/certificates/put_fingerprint.py
lxd_client/api/cluster/__init__.py
lxd_client/api/cluster/delete_cluster_members_by_name.py
lxd_client/api/cluster/get_cluster.py
lxd_client/api/cluster/get_cluster_members.py
lxd_client/api/cluster/get_cluster_members_by_name.py
lxd_client/api/cluster/post_cluster_members_by_name.py
lxd_client/api/cluster/put_cluster.py
lxd_client/api/events/__init__.py
lxd_client/api/events/get_events.py
lxd_client/api/images/__init__.py
lxd_client/api/images/delete_images_aliases_by_name.py
lxd_client/api/images/delete_images_fingerprint.py
lxd_client/api/images/get_images.py
lxd_client/api/images/get_images_aliases.py
lxd_client/api/images/get_images_aliases_by_name.py
lxd_client/api/images/get_images_by_fingerprint_export.py
lxd_client/api/images/get_images_fingerprint.py
lxd_client/api/images/get_images_fingerprint_refresh.py
lxd_client/api/images/patch_images_aliases_by_name.py
lxd_client/api/images/patch_images_fingerprint.py
lxd_client/api/images/post_images.py
lxd_client/api/images/post_images_aliases.py
lxd_client/api/images/post_images_aliases_by_name.py
lxd_client/api/images/post_images_fingerprint_export.py
lxd_client/api/images/post_images_fingerprint_secret.py
lxd_client/api/images/put_images_aliases_by_name.py
lxd_client/api/images/put_images_fingerprint.py
lxd_client/api/instances/__init__.py
lxd_client/api/instances/delete_instances_by_name.py
lxd_client/api/instances/delete_instances_by_name_backups_by_name.py
lxd_client/api/instances/delete_instances_by_name_console.py
lxd_client/api/instances/delete_instances_by_name_files.py
lxd_client-1.0.0.dist-info/WHEEL
lxd_client-1.0.0.dist-info/METADATA
lxd_client-1.0.0.dist-info/RECORD
